[
  {
    "doc_id": "Knowledge-Aided Semantic Communication Leveraging Probabilistic Graphical Modeling [arXiv 2408.04499v1]",
    "filename": "Knowledge-Aided Semantic Communication Leveraging Probabilistic Graphical Modeling [arXiv 2408.04499v1].pdf",
    "page_start": 1,
    "page_end": 1,
    "heading": "Knowledge-Aided Semantic Communication Leveraging Probabilistic Graphical Modeling",
    "text": "Haowen Wan 1 , 2 , Qianqian Yang 2 , Jiancheng Tang 2 , Zhiguo Shi 1 , 2 , 3\n1 Polytechnic Institute, Zhejiang University, Hangzhou, China\n2 College of Information Science and Electronic Engineering, Zhejiang University, Hangzhou, China\n3 Jinhua Institute of Zhejiang University, Jinhua, China\nEmail: { haowenwan20, qianqianyang20, jianchengtang, shizg } @zju.edu.cn\nAbstract -In this paper, we propose a semantic communication approach based on probabilistic graphical model (PGM). The proposed approach involves constructing a PGM from a training dataset, which is then shared as common knowledge between the transmitter and receiver. We evaluate the importance of various semantic features and present a PGM-based compression algorithm designed to eliminate predictable portions of semantic information. Furthermore, we introduce a technique to reconstruct the discarded semantic information at the receiver end, generating approximate results based on the PGM. Simulation results indicate a significant improvement in transmission efficiency over existing methods, while maintaining the quality of the transmitted images.\nIndex Terms -Semantic communication, Image transmission, Probabilistic graphical model\n",
    "figures": [],
    "tables": [],
    "footnotes": []
  },
  {
    "doc_id": "Knowledge-Aided Semantic Communication Leveraging Probabilistic Graphical Modeling [arXiv 2408.04499v1]",
    "filename": "Knowledge-Aided Semantic Communication Leveraging Probabilistic Graphical Modeling [arXiv 2408.04499v1].pdf",
    "page_start": 1,
    "page_end": 2,
    "heading": "I. INTRODUCTION",
    "text": "Data-intensive applications like ultra-high-definition (UHD) video transmission, autonomous driving, mixed reality (MR), and the metaverse are driving a surge in wireless data traffic, posing challenges for existing wireless systems [1]. Semantic communication (SemCom) stands out as a promising technology that greatly enhances transmission efficiency by transmitting compact semantic information while discarding semantically insignificant content. In contrast to conventional communication systems, which prioritize transmitting symbols while ignoring their underlying meaning, SemCom approaches focus on transmitting and retrieving task-relevant information rather than aiming for precise bit recovery. SemCom has demonstrated its superiority in terms of transmission efficiency, particularly in harsh channel conditions. [2].\nDriven by the advantages offered by SemCom, existing work harnesses recent advancements in deep learning techniques to achieve remarkable performance in transmitting various signals such as text [3], speech [4], image [5]-[7], and video [8] signals. In these DL-based semantic communication systems, we can interpret the neural network (NN) weights as knowledge acquired from the training dataset, which is utilized for extracting and recovering semantic information. Typically, the semantic information is perceived as the intermediate latent features output by specific neural network layers. In this way, the semantic information varies in both formats and values when a different NN model is used, lacking a coherent and easily interpretable representation, thereby weakening the generalization ability of SemCom systems across various transmission tasks.\nTo establish a comprehensive SemCom framework, defining a unified representation of semantic information is crucial. Existing approaches include propositional logic, knowledge graphs, and Probabilistic Graphical Models (PGMs), among which PGMs stand out as particularly promising. PGMs are a widely used graphical method for depicting statistical relationships among variables. A PGM consists of nodes, edges, and parameters: nodes represent variables or real-world objects, edges denote relationships between nodes, and parameters capture probabilistic factors. PGMs are extensively employed in the semantic analysis and comprehension of various data types, including text [9], images, and video [10], demonstrating their generality in characterizing semantic information. Motivated by this, several studies have integrated PGMs into SemCom system design. For instance, [11] proposed a SemCom system for text transmission utilizing PGMs to represent shared knowledge about text data between transmitters and receivers. This approach enabled text compression at the transmitter and subsequent recovery at the receiver, reducing signal redundancy. However, this method is limited to text transmission, highlighting the need for further exploration of PGM-based SemCom approaches for other transmission tasks.\nIn this paper, we propose a SemCom approach based on PGM, where a PGM is trained on data and employed as shared semantic knowledge between the transmitter and receiver to minimize transmission redundancy. Specifically, we introduce a PGM-based compression algorithm for semantic information by eliminating easily predictable features through PGM inference, while considering the importance of these features. The receiver then restores the discarded semantic information through inference with the shared PGM using the received semantic data. To evaluate the effectiveness of the proposed framework, we develop a PGM-based SemCom system for facial image transmission. Specifically, we utilize Semantic StyleGAN [12] to extract disentangled semantic features and train a PGM to characterize the statistical correlations between them. Simulation results demonstrate a significant improvement in transmission efficiency compared to existing methods, while preserving the quality of transmitted images.\n",
    "figures": [
      {
        "page": 2,
        "bbox": [
          55.04862976074219,
          739.4477157592773,
          511.7063293457031,
          560.5081787109375
        ],
        "image_path": "/home/preritubuntu/RAG projext/data/extracted_images/picture_1.png",
        "caption": "Fig. 1. The overall structure of the proposed semantic communication system for image transmission",
        "description": "Okay, here's a detailed analysis of the image provided, focusing solely on describing its content as accurately as possible using UTF-8 characters:\n\n**Overall Structure:**\n\nThe image is a diagram illustrating a system architecture, likely related to generative modeling or representation learning. It's divided into two main sections: a \"Knowledge Base\" and two interconnected processing units labeled \"Transmitter\" and \"Receiver.\"  Arrows indicate the flow of data between components.\n\n**Knowledge Base (Top Section):**\n\n*   A rectangular box labeled \"Knowledge Base.\"\n*   Within this box, there's an arrow pointing from a \"Dataset\" to a \"Semantic Encoder\".\n*   Another arrow indicates \"PGM Training,\" connecting the Semantic Encoder to a central node labeled \"PGM\".\n*   The \"PGM\" node has two arrows leading out: one labeled \"Share\" and another labeled \"Noise.\"\n\n**Transmitter (Left Section):**\n\n*   Labeled \"Transmitter\".\n*   A box containing an image of a female face.\n*   An arrow labeled \"F\" originates from the face box and connects to a \"Semantic Encoder\".\n*   The Semantic Encoder's output is connected to a \"PGM Compression\" block.\n*   \"PGM Compression\" has two outputs: one labeled \"L\" and another labeled \"X.\"\n*   \"X\" then flows into a \"Channel Encoder.\"\n*   The Channel Encoder's output is labeled \"KL\".\n\n**Receiver (Right Section):**\n\n*   Labeled \"Receiver\".\n*   A box containing an image of a female face.\n*   An arrow labeled \"F'\" originates from the face box and connects to a \"PGM Decoder.\"\n*   The PGM Decoder's output is labeled \"I\".\n*   \"I\" then flows into a \"Channel Decoder.\"\n*   The Channel Decoder's output is labeled \"KL'.\"\n\n**Connections & Labels:**\n\n*   Arrows are used extensively to represent data flow.\n*   Labels on the arrows include: \"F\", \"F'\", \"L\", \"X\", \"KL\", \"KL'\", \"I\".\n*   The PGM (Probabilistic Generative Model) is represented as a central node with connections labeled \"Share\" and \"Noise.\"\n\n**Color Coding:**\n\n*   The diagram uses distinct colors for different components: blue, red, and gray.  This color coding appears to"
      }
    ],
    "tables": [],
    "footnotes": []
  },
  {
    "doc_id": "Knowledge-Aided Semantic Communication Leveraging Probabilistic Graphical Modeling [arXiv 2408.04499v1]",
    "filename": "Knowledge-Aided Semantic Communication Leveraging Probabilistic Graphical Modeling [arXiv 2408.04499v1].pdf",
    "page_start": 2,
    "page_end": 2,
    "heading": "II. SYSTEM MODEL",
    "text": "In this section, we present the system model of the proposed SemCom approach. We also introduce the definition of compression ratio and metrics to evaluate the performance of the proposed model for image transmission.\n",
    "figures": [],
    "tables": [],
    "footnotes": []
  },
  {
    "doc_id": "Knowledge-Aided Semantic Communication Leveraging Probabilistic Graphical Modeling [arXiv 2408.04499v1]",
    "filename": "Knowledge-Aided Semantic Communication Leveraging Probabilistic Graphical Modeling [arXiv 2408.04499v1].pdf",
    "page_start": 2,
    "page_end": 2,
    "heading": "A. Knowledge Base",
    "text": "As shown in Fig. 1, we learn a PGM from a given dataset that shares the same distribution as the data to be transmitted later. The original data in the training set are first disentangled into latent representations using a semantic encoder. We then use a Bayesian network (BN), a directed acyclic graph (DAG) composed of nodes and edges, to represent directional causality and conditional probability distributions (CPDs) among the semantic features. The nodes in the BN correspond to semantic features extracted by the semantic encoder, and the directional edges are determined by a structural learning algorithm. The CPDs in the BN are estimated using a parameter learning algorithm. This BN, along with other training results, forms the knowledge base of the proposed model, which is shared by the transmitter and receiver for inference.\n",
    "figures": [],
    "tables": [],
    "footnotes": []
  },
  {
    "doc_id": "Knowledge-Aided Semantic Communication Leveraging Probabilistic Graphical Modeling [arXiv 2408.04499v1]",
    "filename": "Knowledge-Aided Semantic Communication Leveraging Probabilistic Graphical Modeling [arXiv 2408.04499v1].pdf",
    "page_start": 2,
    "page_end": 2,
    "heading": "B. Transmitter",
    "text": "The transmitter in the considered SemCom system consists of a semantic encoder, a PGM compression module, and a channel encoder. First, the semantic encoder extracts a compact latent semantic representation, denoted as L , from the original data F . The PGM compression module then uses the PGM's inference results to filter out the part of the latent code that can be easily inferred, resulting in a reduced latent representation, denoted as L ′ . The channel encoder maps L ′ into a symbol sequence X for transmission over the physical channel. It is crucial for the receiver to know the exact indices of the preserved features, denoted as KL , to reconstruct the original image. Therefore, KL is transmitted losslessly using digital communication techniques.\n",
    "figures": [],
    "tables": [],
    "footnotes": []
  },
  {
    "doc_id": "Knowledge-Aided Semantic Communication Leveraging Probabilistic Graphical Modeling [arXiv 2408.04499v1]",
    "filename": "Knowledge-Aided Semantic Communication Leveraging Probabilistic Graphical Modeling [arXiv 2408.04499v1].pdf",
    "page_start": 2,
    "page_end": 2,
    "heading": "C. Receiver",
    "text": "The received signal at the receiver is given by\nwhere N ∼ N ( 0 , σ 2 ) denotes the Gaussian noise of the channel. The receiver consists of a channel decoder, a PGM decompression module, and a semantic decoder. The received signal Y is first mapped back into the latent semantic representation ˆ L ′ by the channel decoder. Then, the PGM decompression module uses ˆ L ′ and their corresponding indices KL to recover the discarded latent features through PGM inference. Eventually, the semantic decoder combines ˆ L ′ and the inferred latent features to reconstruct the image ˆ F .\n",
    "figures": [],
    "tables": [],
    "footnotes": []
  },
  {
    "doc_id": "Knowledge-Aided Semantic Communication Leveraging Probabilistic Graphical Modeling [arXiv 2408.04499v1]",
    "filename": "Knowledge-Aided Semantic Communication Leveraging Probabilistic Graphical Modeling [arXiv 2408.04499v1].pdf",
    "page_start": 2,
    "page_end": 3,
    "heading": "D. Metrics",
    "text": "We evaluate our system's performance for an image transmission task in terms of image reconstruction quality and bandwidth compression ratio. To assess image reconstruction quality, we use two widely adopted metrics: Peak Signal-toNoise Ratio (PSNR) and Learned Perceptual Image Patch Similarity (LPIPS) [13]. PSNR measures the pixel-level difference between two images, denoted by\nwhere Max ( F, ˆ F ) 2 represents the maximum difference between pixel values in the images. LPIPS measures the distance in the feature space derived by the pre-trained AlexNet from a human perceptual perspective, denoted by\nwhere f l i,j and ˆ f l i,j denote the ( i, j ) th element in normalized latent feature maps output by layer l of the AlexNet, respectively. H l and W l denote the height and width of the feature map, respectively. Notation ⊙ denotes the scale operation and c l represents the pretrained weights for intermediate latent output by layer l .\nWe employ bandwidth compression ratio to evaluate the transmission efficiency. We define the image dimension n as the source bandwidth, and the channel dimension k as the channel bandwidth. We denote the ratio kn as the bandwidth compression ratio.\n",
    "figures": [],
    "tables": [],
    "footnotes": []
  },
  {
    "doc_id": "Knowledge-Aided Semantic Communication Leveraging Probabilistic Graphical Modeling [arXiv 2408.04499v1]",
    "filename": "Knowledge-Aided Semantic Communication Leveraging Probabilistic Graphical Modeling [arXiv 2408.04499v1].pdf",
    "page_start": 3,
    "page_end": 3,
    "heading": "III. PROPOSED METHOD",
    "text": "In this section, we introduce a PGM-based SemCom approach for facial image transmission. We begin by explaining the inversion method of Semantic StyleGAN, followed by the introduction of PGM training. Next, we present the compression and decompression algorithms for the decoupled latent code. Finally, we outline the training procedures for the channel encoder and decoder.\n",
    "figures": [],
    "tables": [],
    "footnotes": []
  },
  {
    "doc_id": "Knowledge-Aided Semantic Communication Leveraging Probabilistic Graphical Modeling [arXiv 2408.04499v1]",
    "filename": "Knowledge-Aided Semantic Communication Leveraging Probabilistic Graphical Modeling [arXiv 2408.04499v1].pdf",
    "page_start": 3,
    "page_end": 3,
    "heading": "A. Semantic Encoder and Decoder",
    "text": "To extract disentangled semantic information from input image x , we leverage the inversion method [14] of Semantic StyleGAN generative function, denoted by G ( · ) , for semantic encoding and decoding. The semantic encoder aims to find the semantic information of the input image, which can be used to generate an image most similar to the original using the generative function G ( · ) . This process can be formulated as the following optimization problem:\nwhere L represents the extracted disentangled latent information of the input image F , λ 1 and λ 2 are hyperparameters used to balance the l2-norm loss and LPIPS loss. This optimization problem can be effectively solved using gradient descent methods.\nThe semantic decoder utilizes the generative function of Semantic StyleGAN to decode the recovered latent representation ˆ L . The generation process can be expressed as\nwhere ˆ F is the reconstructed image.\n",
    "figures": [],
    "tables": [],
    "footnotes": []
  },
  {
    "doc_id": "Knowledge-Aided Semantic Communication Leveraging Probabilistic Graphical Modeling [arXiv 2408.04499v1]",
    "filename": "Knowledge-Aided Semantic Communication Leveraging Probabilistic Graphical Modeling [arXiv 2408.04499v1].pdf",
    "page_start": 3,
    "page_end": 3,
    "heading": "B. Construction of Probabilistic Graphical Model",
    "text": "In this paper, we utilize the first 28,000 images from the CelebA-HQ dataset [15] for training and preprocessing the images in the dataset before constructing the Bayesian network (BN). Given the large scale of the dataset, analysing each latent code one by one not only causes a large computational cost, but also is not conducive to finding the probabilistic relations between semantic features. To address the problem, we consider using the Mini-Batch Kmeans algorithm to compress the domain of each semantic feature.\nAfter the above preparation, we utilize bnlearn [16] to complete the parameter learning and structure learning of BN. We choose score-based structure learning and utilize the HillClimbSearch algorithm for constructing BN. As for parameters, we employ Maximum Likelihood Estimation (MLE) for parameter estimation based on training data. During the search, we adopt Bayesian Information Criterion (BIC) for selecting the best model from a finite set of model. Given the dataset D , BIC scoring function of Bayesian network B = ⟨ G, Θ ⟩ can be written as:\nwhere | B | is the number of parameters in BN, LL ( B | D ) is the the logarithmic likelihood of BN. As depicted in Fig.2, we ultimately obtain a Bayesian network trained on the CelebAHQ dataset for prediction and inference.\n",
    "figures": [
      {
        "page": 3,
        "bbox": [
          312.3302307128906,
          740.860969543457,
          526.1447143554688,
          566.6690826416016
        ],
        "image_path": "/home/preritubuntu/RAG projext/data/extracted_images/picture_2.png",
        "caption": "Fig. 2. Bayesian network trained on CelebA-HQ dataset",
        "description": "Okay, here's a detailed analysis of the image as a scientific/technical document graphic, focusing solely on describing its contents without interpretation:\n\n**Image Description:**\n\nThe image is a directed graph visualization. It represents relationships between various textual labels (nodes) connected by arrows (edges). The nodes are arranged in a roughly circular pattern with varying sizes.  The background color is white.\n\n**Nodes (Labels):**\n\nThere are 30 distinct nodes, each labeled with a string of text. Here's a list of the nodes and their associated labels:\n\n1.  feature25\n2.  feature23\n3.  glass\n4.  hat\n5.  mouth shape\n6.  ear shape\n7.  background\n8.  background2\n9.  eye texture\n10. eyebrow texture\n11. eyebrow shape\n12. eyelash shape\n13. hair shape\n14. hair texture\n15. coarse profile2\n16. coarse profile1\n17. face texture\n18. nose texture\n19. nose shape\n20. neck shape\n21. ear texture\n22. earring\n23. cloth shape\n24. cloth texture\n25. mouth texture\n26. neck texture\n27. feature27\n28. face shape\n29.  carrying\n30.  skin texture\n\n**Edges (Arrows):**\n\n*   There are 61 directed edges connecting the nodes. The direction of each arrow indicates a relationship.\n*   The arrows connect nodes in various configurations: one-to-one, one-to-many, and many-to-many.\n*   Some edges have line thickness that varies.\n\n**Data Points & Patterns:**\n\n*   **Node Size:** Node sizes vary, with several larger nodes (e.g., \"face texture\", \"ear shape\") having a significantly greater size than smaller nodes (e.g., \"glass\", \"hat\").\n*   **Edge Density:** The density of edges varies across the graph. Some clusters have many connections, while others are relatively sparsely connected.\n*   **Connectivity:**  \"Face Texture,\" \"Ear Shape,\" and \"Eye Texture\" each have 6 outgoing edges. \"Coarse Profile2\" has 5 outgoing edges.\n\n**Technical Notes:**\n\n*   The visualization uses a node-link diagram layout.\n*"
      }
    ],
    "tables": [],
    "footnotes": []
  },
  {
    "doc_id": "Knowledge-Aided Semantic Communication Leveraging Probabilistic Graphical Modeling [arXiv 2408.04499v1]",
    "filename": "Knowledge-Aided Semantic Communication Leveraging Probabilistic Graphical Modeling [arXiv 2408.04499v1].pdf",
    "page_start": 3,
    "page_end": 4,
    "heading": "C. Compression and Decompression Algorithm",
    "text": "At the transmitter side, we employ the inversion method of Semantic StyleGAN for semantic information extraction, which also serves as compression for images. Subsequently, we utilize a PGM-based compression algorithm for further compression. Initially, we simulate the inference error of the PGM by replacing it with a random clustering center and measure the LPIPS and MSE to assess the importance of each semantic feature. Based on these results and the structure of the PGM, we retain 14 features as side information for inference and assign weights to the remaining negligible features.\nWith this preparation, we utilize the PGM to compute the correct inference probability of each negligible node based on other nodes, which can be expressed as:\nwhere P 1 is the probabilistic vector of the first round, p i is the correct inference probability of i th node. After multiplying the probability of each node by its weight, we select the highest weighted probability, denoted by:\nwhere W 1 is the weight vector of the first round. We then find the node corresponding to p max 1 and discard its dimension SNR=-5dB\nSNR=-1dB\nin the latent code. This process is repeated several times until we obtain the compressed latent code and the list of retained dimensions.\nThe compression algorithm's concept is applied to the decompression algorithm, enabling the deduction of missing dimensions by the PGM. At the receiver side, upon receiving the compressed latent code, the system infers the most likely corresponding state of each ignored node based on the PGM. Subsequently, it selects the highest probability p ′ max 1 in the probabilistic vector, which can be written as:\nwhere P ′ 1 is the probabilistic vector of the first round, p ′ j is the probability of the most likely corresponding state of j th node. The node and its state corresponding to p ′ 1 is assumed as known information, and its dimension in latent code is then replaced by the clustering center of its approximate state. This process is repeated until the omitted dimensions in the latent code are recovered, resulting in the decompressed latent code.\n",
    "figures": [
      {
        "page": 4,
        "bbox": [
          71.38972473144531,
          732.5281295776367,
          258.92486572265625,
          581.2193450927734
        ],
        "image_path": "/home/preritubuntu/RAG projext/data/extracted_images/picture_3.png",
        "caption": "Fig. 3. PSNR versus SNR for different approaches. The compression ratios are listed in the legend.",
        "description": "Here's an analysis of the image based solely on its visual content:\n\n**Image Description:**\n\nThe image is a line graph depicting the relationship between Signal-to-Noise Ratio (SNR) and Peak Signal-to-Noise Ratio (PSNR) for three different methods. The graph uses a logarithmic scale for both the x and y axes.\n\n**Axes:**\n\n*   **X-axis:**  Signal-to-Noise Ratio (SNR), ranging from -5 to 5.\n*   **Y-axis:** Peak Signal-to-Noise Ratio (PSNR), ranging from approximately 10 to 30.\n\n**Lines and Data Points:**\n\n*   **Blue Line (DeepLab C 148):** A dashed line with blue circles representing the PSNR values for a method labeled \"DeepLab C 148\".\n    *   At SNR = 0, PSNR = 27.6\n    *   At SNR = 1, PSNR = 28.3\n    *   At SNR = 2, PSNR = 28.7\n    *   At SNR = 3, PSNR = 29.1\n    *   At SNR = 4, PSNR = 29.5\n    *   At SNR = 5, PSNR = 29.9\n\n*   **Red Line (Our Method 1/108):** A dashed line with red triangles representing the PSNR values for a method labeled \"Our Method 1/108\".\n    *   At SNR = 0, PSNR = 16.3\n    *   At SNR = 1, PSNR = 16.7\n    *   At SNR = 2, PSNR = 17.1\n    *   At SNR = 3, PSNR = 17.5\n    *   At SNR = 4, PSNR = 17.9\n    *   At SNR = 5, PSNR = 18.3\n\n*   **Orange Line (Our Method 1/109):** A dashed line with orange squares representing the PSNR values for a method labeled \"Our Method 1/109\".\n    *   At SNR = 0, PSNR = 15.7\n    *   At SNR = 1, PSNR = 1"
      },
      {
        "page": 4,
        "bbox": [
          52.382415771484375,
          518.9881591796875,
          100.834228515625,
          420.2281494140625
        ],
        "image_path": "/home/preritubuntu/RAG projext/data/extracted_images/picture_4.png",
        "caption": "",
        "description": "Here's an analysis of the image based on observable features, adhering to your specifications:\n\n**Image Description:**\n\nThe image is a composite graphic consisting of two distinct photographic images arranged vertically. The overall background color is black.\n\n**Top Image:**\n\n*   **Subject:** A female subject with dark brown hair styled in loose waves.\n*   **Facial Features:**  She has light skin, blue eyes, and a neutral facial expression. Her lips are slightly parted.\n*   **Lighting:** The lighting appears to be diffused and even across the face.\n\n**Bottom Image:**\n\n*   **Subject:** A male subject with dark brown hair styled in a longer, more textured manner.\n*   **Facial Features:** He has fair skin, brown eyes, and a neutral facial expression. His lips are slightly parted.\n*   **Lighting:** The lighting appears to be diffused and even across the face.\n\n**Text Overlay:**\n\n*   A text label \"Original\" is positioned below the bottom image. \n\n**Data Points & Patterns:**\n\n*   The images are presented side-by-side, with a clear vertical separation between them.\n*   Both subjects exhibit similar facial features (eyes, nose, mouth) but differ in hair color and style, as well as skin tone.\n*   The image is digitally manipulated to combine these two separate photographs into one composite."
      },
      {
        "page": 4,
        "bbox": [
          113.842529296875,
          534.0556640625,
          208.48062133789062,
          420.069091796875
        ],
        "image_path": "/home/preritubuntu/RAG projext/data/extracted_images/picture_5.png",
        "caption": "Original",
        "description": "Here's an analysis of the image based on scientific/technical document conventions:\n\n**Image Description:**\n\nThe image is a four-panel display comparing two facial image processing techniques, labeled \"Proposed\" and \"Deep JSC.\" Each panel contains a rendered face image. The images are presented side-by-side within a white border. \n\n**Panel Breakdown:**\n\n*   **Top Left (Proposed):** Displays an image of a woman with dark brown hair, fair skin, and a serious expression.\n*   **Top Right (Deep JSC):** Displays an image of a woman with dark brown hair, fair skin, and a serious expression. The image appears to have undergone significant blurring or smoothing compared to the \"Proposed\" panel.\n*   **Bottom Left (Proposed):** Displays an image of a man with dark brown hair, a goatee, and a neutral expression.\n*   **Bottom Right (Deep JSC):** Displays an image of a man with dark brown hair, a goatee, and a neutral expression. The image appears to have undergone significant blurring or smoothing compared to the \"Proposed\" panel.\n\n**Text:**\n\nThe text labels are positioned in the top left corner: \"Proposed\" and \"Deep JSC\".  Below the images, there is text indicating the Structural Similarity Index Metric (SSIM) score for each comparison: \"SSIM = 0.68\".\n\n**Data Points/Patterns:**\n\n*   Two face images are presented for both techniques.\n*   The \"Deep JSC\" panels show a noticeable increase in image blur or smoothing compared to the corresponding \"Proposed\" panels.\n*   A numerical value (SSIM = 0.68) is provided, representing a quantitative measure of similarity between the two images."
      },
      {
        "page": 4,
        "bbox": [
          226.17503356933594,
          528.5016479492188,
          317.29833984375,
          427.6200256347656
        ],
        "image_path": "/home/preritubuntu/RAG projext/data/extracted_images/picture_6.png",
        "caption": "",
        "description": "Here's an analysis of the image based on scientific/technical document standards, using UTF-8 characters:\n\n**Image Description:**\n\nThe image is a composite graphic depicting two facial renderings of human subjects presented side-by-side. The graphic is divided into four panels arranged in a 2x2 grid.\n\n*   **Panel 1 (Top Left):** Displays an image of a female subject with light skin, brown hair, and blue eyes.  The lighting appears to be soft and diffused.\n*   **Panel 2 (Top Right):** Displays an image of a female subject with darker skin, dark brown hair, and brown eyes. The lighting is similar to Panel 1.\n*   **Panel 3 (Bottom Left):** Displays an image of a male subject with dark skin, short dark hair, and dark eyes.  The lighting appears to be directional.\n*   **Panel 4 (Bottom Right):** Displays an image of a male subject with light skin, short dark hair, and dark eyes. The lighting is similar to Panel 3.\n\n**Text:**\n\nThe graphic contains two labels positioned above the respective panels:\n\n*   \"Proposed\" -  Located above Panel 1 & 2\n*   \"Deep JSC\" - Located above Panel 3 & 4\n\n**Data Points/Patterns:**\n\n*   The image presents four distinct facial renderings.\n*   Each rendering represents a different subject with varying skin tones, hair colors, and eye colors.\n*   The lighting conditions appear to be consistent across all panels (though slightly directional in Panels 3 & 4).\n*   The images are presented as comparisons between two different processing methods or models (\"Proposed\" and \"Deep JSC\")."
      },
      {
        "page": 4,
        "bbox": [
          342.8990783691406,
          732.8008499145508,
          534.41796875,
          581.5228729248047
        ],
        "image_path": "/home/preritubuntu/RAG projext/data/extracted_images/picture_7.png",
        "caption": "",
        "description": "Here's an analysis of the image based solely on its visual content:\n\n**Image Description:**\n\nThe image is a line graph depicting performance metrics across varying Signal-to-Noise Ratios (SNR). The graph displays four data sets represented by different colored lines.\n\n**Axes:**\n\n*   **X-axis:** Signal-to-Noise Ratio (SNR), ranging from 0 to approximately 5.\n*   **Y-axis:** Linear Probability (LP86_), ranging from approximately 0.5 to 0.7.\n\n**Data Sets & Lines:**\n\n1.  **Deep ISOCC 148:** A blue line with circular markers. The data points decrease consistently as SNR increases.\n2.  **Our Method 1/54:** A dark green line with square markers. The data points also decrease consistently as SNR increases, but at a slightly different rate than the Deep ISOCC 148 line.\n3.  **Our Method 1/100:** A light green line with triangular markers. This line exhibits a similar downward trend to the \"Our Method 1/54\" line, though it appears to have a steeper slope.\n4. **Deep ISOCC 148**: A blue line with circular markers. The data points decrease consistently as SNR increases.\n\n**Trends & Patterns:**\n\n*   All four lines demonstrate a negative correlation between SNR and Linear Probability (LP86_). As the SNR increases, LP86_ decreases.\n*   The Deep ISOCC 148 line exhibits the highest initial value of LP86_ at SNR = 0.\n*   The \"Our Method 1/54\" and \"Our Method 1/100\" lines have similar trends but differ in their slopes, indicating potentially different performance characteristics between the two methods.\n\n**Text:**\n\nThe graph title is \"Deep ISOCC 148\". The x-axis label reads \"SNR\" and the y-axis label reads \"LP86_\"."
      },
      {
        "page": 4,
        "bbox": [
          338.5916442871094,
          529.9207153320312,
          432.7919616699219,
          426.85357666015625
        ],
        "image_path": "/home/preritubuntu/RAG projext/data/extracted_images/picture_8.png",
        "caption": "SNR=1dB",
        "description": "Here's an analysis of the image based on observable details:\n\n**Image Description:**\n\nThe image is a four-panel display comparing two face reconstruction methods, labeled \"Proposed\" and \"Deep JSCC.\" The panels are arranged in a 2x2 grid.\n\n**Panel Breakdown:**\n\n*   **Top Left (Proposed):** Displays an image of a female subject with brown hair, light skin, blue eyes, and a neutral expression.  The facial features appear relatively sharp and well-defined.\n*   **Top Right (Deep JSCC):** Displays an image of the same female subject as the top left panel. The reconstruction shows a noticeable blurring or softening of the facial details compared to the \"Proposed\" panel. Color saturation appears slightly increased.\n*   **Bottom Left (Proposed):** Displays an image of a male subject with dark hair, light skin, brown eyes, and a neutral expression.  The facial features appear relatively sharp and well-defined.\n*   **Bottom Right (Deep JSCC):** Displays an image of the same male subject as the bottom left panel. The reconstruction shows a blurring effect similar to that observed in the top right panel, with increased color saturation.\n\n**Text:**\n\n*   The text \"Proposed\" is positioned above the top-left panel.\n*   The text \"Deep JSCC\" is positioned above the top-right panel. \n\n**Data Points/Patterns:**\n\n*   The image presents two different face reconstructions of the same individuals.\n*   There's a clear difference in the level of detail and sharpness between the original images and the reconstructed versions. The \"Deep JSCC\" method consistently produces a softer, more blurred reconstruction compared to the \"Proposed\" method.\n*   Both methods exhibit increased color saturation in their reconstructions relative to the original input images."
      },
      {
        "page": 4,
        "bbox": [
          452.81683349609375,
          530.3454895019531,
          547.21044921875,
          426.6000671386719
        ],
        "image_path": "/home/preritubuntu/RAG projext/data/extracted_images/picture_9.png",
        "caption": "SNR=5dB",
        "description": "Here's an analysis of the image based on its observable content:\n\n**Image Description:**\n\nThe image is a two-by-two grid of photographs presented side-by-side, likely from a scientific or technical document. The images are labeled \"Proposed\" and \"Deep JSCC\" in white text across the top of the respective columns. \n\n**Top Left Image (Labeled \"Proposed\"):**\n*   It depicts a portrait of a young woman with dark brown hair and light skin.\n*   Her facial features include blue eyes, full lips, and a slightly smiling expression.\n*   The lighting appears to be soft and diffused.\n\n**Top Right Image (Labeled \"Deep JSCC\"):**\n*   This image also depicts a portrait of a young woman with dark brown hair. \n*   The skin tone is significantly darker than the \"Proposed\" image, exhibiting a reddish hue.\n*   Her facial features are similar to the first image but with altered lighting and color grading.\n\n**Bottom Left Image (Labeled \"Proposed\"):**\n*   This image depicts a portrait of a young man with dark brown hair and fair skin.\n*   He has light eyes, full lips, and a neutral expression.\n*   The lighting is similar to the top left image.\n\n**Bottom Right Image (Labeled \"Deep JSCC\"):**\n*   This image depicts a portrait of a young man with dark brown hair. \n*   The skin tone is significantly darker than the \"Proposed\" image, exhibiting a reddish hue.\n*   His facial features are similar to the bottom left image but with altered lighting and color grading.\n\n**Overall Observations:**\n\n*   The images appear to be comparisons of two different methods or algorithms (likely related to face processing) - \"Proposed\" and \"Deep JSCC\".\n*   Both methods produce portraits of individuals, but the \"Deep JSCC\" method consistently generates a darker skin tone with a reddish hue compared to the \"Proposed\" method. \n*   The images are presented in a side-by-side format for direct visual comparison."
      }
    ],
    "tables": [],
    "footnotes": []
  },
  {
    "doc_id": "Knowledge-Aided Semantic Communication Leveraging Probabilistic Graphical Modeling [arXiv 2408.04499v1]",
    "filename": "Knowledge-Aided Semantic Communication Leveraging Probabilistic Graphical Modeling [arXiv 2408.04499v1].pdf",
    "page_start": 4,
    "page_end": 4,
    "heading": "D. Channel Encoder and Decoder",
    "text": "In this system, the compressed latent codes generated by the PGM cannot be transmitted as a whole. Due to the variability in images, the PGM may opt to ignore different features, and the number of neglected features may vary depending on the channel's state. To address this challenge, we employ 28 sets of channel encoders and decoders, each comprising a cascaded FC layer. All sets of encoders and decoders are encapsulated within a neural network, allowing for the invocation of the appropriate channel encoders and decoders for different numbers of dimensions of latent codes. We adopt an end-to-end training strategy to train the network and utilize Mean Squared Error (MSE) as the loss function. The loss function calculates the MSE between the compressed latent code and the reconstructed latent code.\n",
    "figures": [],
    "tables": [],
    "footnotes": []
  },
  {
    "doc_id": "Knowledge-Aided Semantic Communication Leveraging Probabilistic Graphical Modeling [arXiv 2408.04499v1]",
    "filename": "Knowledge-Aided Semantic Communication Leveraging Probabilistic Graphical Modeling [arXiv 2408.04499v1].pdf",
    "page_start": 4,
    "page_end": 5,
    "heading": "IV. SIMULATION",
    "text": "In this section, we evaluate the performance of proposed semantic communication system in terms of the transmission efficiency and robustness. We use CelebA-HQ dataset for training and testing. For simulating transmission on a real channel, we assume AWGN channel simulate the channels under different SNR. We use the existing semantic communication approach by [6], referred to as Deep JSCC, as the benchmark approach to compare to. We note that all approaches are trained and tested with the same datasets.\nDuring training, we set AWGN channel conditions with SNR randomly varying from -5dB to 5dB.\nThe performance comparison of different approaches in terms of PSNR and LPIPS is presented in Fig.3 and Fig.4. A higher PSNR indicates better pixel-level restoration, while smaller LPIPS scores signify better objective perception restoration. It can be observed that with a 50% compression ratio of Deep JSCC, our method achieves slightly lower PSNR scores but better LPIPS scores. This demonstrates that the proposed system preserves image perception well while endeavoring to maintain image details as much as possible. Furthermore, we find that PSNR and LPIPS values obtained by our approach remain almost unchanged under different SNRs, indicating the robustness of the proposed system to noisy channels.Fig.5 illustrates examples of reconstructed images produced by Deep JSCC and the proposed method, corroborating our results directly.\nAdditionally, we compare the performance of different compression ratios in terms of PSNR. During both training and testing, we set the Additive White Gaussian Noise (AWGN) channel conditions with an SNR of 5dB. The PSNR and LPIPS values obtained by our method, as depicted in Fig.6, also exhibit stability under varying compression ratios, further validating the robustness of our method to losses in transmitted information. Subsequently, we evaluate the effect of the PGM in Fig.7. During both training and testing, we maintain AWGN channel conditions with an SNR of 22dB. We observe that the PSNR of images decompressed by the PGM is significantly higher than those decompressed randomly, demonstrating that the PGM aids in reconstructing images with higher quality. Additionally, we note that the PSNR values in both situations are very close, indicating that the preserved features effectively control the style of the original images.\n",
    "figures": [
      {
        "page": 5,
        "bbox": [
          71.49807739257812,
          732.6474761962891,
          261.79327392578125,
          581.1374664306641
        ],
        "image_path": "/home/preritubuntu/RAG projext/data/extracted_images/picture_10.png",
        "caption": "Fig. 6. PSNR versus compression ratio, SNR=-5dB, 0dB, 5dB.",
        "description": "Here's an analysis of the image based on its visual content:\n\n**Image Description:**\n\nThe image is a line graph depicting the Peak Signal-to-Noise Ratio (PSNR) values for two methods, labeled \"Our Method Soft\" and \"Our Method Hard,\" as a function of Compression Ratio.\n\n**Axes:**\n\n*   **X-axis:** Represents the Compression Ratio, ranging from 1/100 to 1/54. The scale is marked in increments of 1/10.\n*   **Y-axis:** Represents PSNR (Peak Signal-to-Noise Ratio), measured in dB (decibels). The scale ranges from approximately 12 to 22, with increments of 2 dB.\n\n**Data Points & Lines:**\n\n*   **\"Our Method Soft\":**  A dashed blue line connects the following data points:\n    *   Compression Ratio 1/100: PSNR = 18.0 dB\n    *   Compression Ratio 1/96: PSNR = 18.2 dB\n    *   Compression Ratio 1/95: PSNR = 18.3 dB\n    *   Compression Ratio 1/90: PSNR = 17.8 dB\n    *   Compression Ratio 1/86: PSNR = 17.4 dB\n    *   Compression Ratio 1/85: PSNR = 17.2 dB\n    *   Compression Ratio 1/80: PSNR = 16.3 dB\n    *   Compression Ratio 1/76: PSNR = 16.0 dB\n    *   Compression Ratio 1/75: PSNR = 16.1 dB\n    *   Compression Ratio 1/70: PSNR = 16.4 dB\n    *   Compression Ratio 1/68: PSNR = 16.5 dB\n    *   Compression Ratio 1/65: PSNR = 16.9 dB\n    *   Compression Ratio 1/63: PSNR = 17.0 dB\n    *   Compression Ratio 1/60: PSNR = 17.8 dB\n    *   Compression Ratio 1/54: PSNR = 18.2 dB\n\n*   **\"Our Method Hard\":** A dashed"
      }
    ],
    "tables": [],
    "footnotes": []
  },
  {
    "doc_id": "Knowledge-Aided Semantic Communication Leveraging Probabilistic Graphical Modeling [arXiv 2408.04499v1]",
    "filename": "Knowledge-Aided Semantic Communication Leveraging Probabilistic Graphical Modeling [arXiv 2408.04499v1].pdf",
    "page_start": 5,
    "page_end": 5,
    "heading": "V. CONCLUSION",
    "text": "This work proposed a SemCom framework based on PGM, leveraging PGM as shared semantic knowledge between the transmitter and receiver for reducing transmission redundancy.\nWe introduced a compression algorithm that discards negligible semantic information, considering the significance of semantic features and inference with PGM. The receiver then recovers the compressed semantic information through inference with the shared PGM. To evaluate the effectiveness of the proposed framework, we develop a PGM-based SemCom system for facial image transmission. Simulation results demonstrate the improvement in efficiency and robustness of the proposed semantic communication framework compared to existing methods.\n",
    "figures": [
      {
        "page": 5,
        "bbox": [
          342.6117248535156,
          732.9289360046387,
          536.909912109375,
          581.1337127685547
        ],
        "image_path": "/home/preritubuntu/RAG projext/data/extracted_images/picture_11.png",
        "caption": "Fig. 7. PSNR versus compression ratio, SNR=22dB.",
        "description": "Here's an analysis of the image based solely on its visual content:\n\n**Image Description:**\n\nThe image is a line graph depicting the Peak Signal-to-Noise Ratio (PSNR) values as a function of compression ratio. The graph is presented in grayscale.\n\n**Axes:**\n\n*   **X-axis:** Represents the \"Compression Ratio,\" ranging from 1.500 to 1.514, with increments of 0.001.\n*   **Y-axis:** Represents \"PSNR,\" ranging from approximately 18.6 to 19.3, with increments of 0.05.\n\n**Lines and Data Points:**\n\nThe graph displays two lines:\n\n1.  **Red Solid Line:** Represents \"Our Method with PGM 1/100\". The data points along this line are approximately:\n    *   (1.500, 18.79)\n    *   (1.525, 18.93)\n    *   (1.550, 18.98)\n    *   (1.575, 19.04)\n    *   (1.600, 19.11)\n    *   (1.625, 19.17)\n    *   (1.650, 19.23)\n    *   (1.675, 19.28)\n    *   (1.700, 19.32)\n\n2.  **Blue Dotted Line:** Represents \"Our Method without PGM 1/100\". The data points along this line are approximately:\n    *   (1.500, 18.79)\n    *   (1.525, 18.86)\n    *   (1.550, 18.93)\n    *   (1.575, 18.98)\n    *   (1.600, 19.04)\n    *   (1.625, 19.09)\n    *   (1.650, 19.15)\n    *   (1.6"
      }
    ],
    "tables": [],
    "footnotes": []
  },
  {
    "doc_id": "Knowledge-Aided Semantic Communication Leveraging Probabilistic Graphical Modeling [arXiv 2408.04499v1]",
    "filename": "Knowledge-Aided Semantic Communication Leveraging Probabilistic Graphical Modeling [arXiv 2408.04499v1].pdf",
    "page_start": 5,
    "page_end": 6,
    "heading": "REFERENCES",
    "text": "E. C. Strinati and S. Barbarossa, '6G networks: Beyond shannon towards semantic and goal-oriented communications,' Comput. Networks , vol. 190, p. 107930, 2021.\nH. Xie, Z. Qin, G. Y. Li, and B. H. Juang, 'Deep learning enabled semantic communication systems,' IEEE Trans. Signal Process. , vol. 69, pp. 2663-2675, Apr. 2021.\nN. Farsad, M. Rao, and A. Goldsmith, 'Deep learning for joint sourcechannel coding of text,' in Proc. IEEE Trans. Acoust. Speech Signal Process(ICASSP) , Calgary, AB, Canada, Apr. 2018, pp. 2326-2330.\nT. Han, Q. Yang, Z. Shi, S. He, and Z. Zhang, 'Semantic-preserved communication system for highly efficient speech transmission,' IEEE J. Sel. Areas Commun. , vol. 41, no. 1, pp. 245-259, Jan. 2023.\nT. Han, J. Tang, Q. Yang, Y. Duan, Z. Zhang, and Z. Shi, 'Generative model based highly efficient semantic communication approach for image transmission,' in Proc. IEEE Trans. Acoust. Speech Signal Process(ICASSP) . IEEE, 2023, pp. 1-5.\nE. Bourtsoulatze, D. B. Kurka, and D. G¨ und¨ uz, 'Deep joint sourcechannel coding for wireless image transmission,' IEEE Trans. Cogn. Commun. Netw. , vol. 5, no. 3, pp. 567-579, Sept. 2019.\nW. Chen, S. Tang, and Q. Yang, 'Enhancing image privacy in semantic communication over wiretap channels leveraging differential privacy,' arXiv preprint arXiv:2405.09234 , May. 2024.\nT. Y. Tung and D. G¨ und¨ uz, 'Deepwive: Deep-learning-aided wireless video transmission,' IEEE J. Sel. Areas Commun. , vol. 40, no. 9, pp. 2570-2583, Sept. 2022.\nF. S. Nurfikri, M. S. Mubarok et al. , 'News topic classification using mutual information and bayesian network,' in International Conference on Information and Communication Technology(ICoICT) , Bandung, Indonesia, May 2018, pp. 162-166.\nC. L. Huang, H. C. Shih, and C. Y. Chao, 'Semantic analysis of soccer video using dynamic bayesian network,' IEEE Trans. Multim. , vol. 8, no. 4, pp. 749-760, Aug. 2006.\nZ. Zhao, Z. Yang, Q. V. Pham, Q. Yang, and Z. Zhang, 'Semantic communication with probability graph: A joint communication and computation design,' in Proc. (IEEE) Veh. Technol. Conf.(VTC) , HongKong, Oct. 2023, pp. 1-5.\nY. Shi, X. Yang, Y. Wan, and X. Shen, 'Semanticstylegan: Learning compositional generative priors for controllable image synthesis and editing,' in Proc. IEEE Conf. Comput. Vis. Pattern Recognit.(CVPR) , New Orleans, Louisiana, Jun. 2022, pp. 11 244-11 254.\nR. Zhang, P. Isola, A. A. Efros, E. Shechtman, and O. Wang, 'The unreasonable effectiveness of deep features as a perceptual metric,' in Proc. IEEE Conf. Comput. Vis. Pattern Recognit.(CVPR) , Salt Lake City, UT, USA, Jun. 2018, pp. 586-595.\nR. Abdal, Y. Qin, and P. Wonka, 'Image2stylegan++: How to edit the embedded images?' in Proc. IEEE Conf. Comput. Vis. Pattern Recognit.(CVPR) , Seattle, WA, USA, Jun. 2020, pp. 8293-8302.\nC. H. Lee, Z. Liu, L. Wu, and P. Luo, 'Maskgan: Towards diverse and interactive facial image manipulation,' in Proc. IEEE Conf. Comput. Vis. Pattern Recognit.(CVPR) , Seattle, WA, USA, Jun. 2020, pp. 5549-5558.\nE. Taskesen, 'Learning Bayesian Networks with the bnlearn Python Package.' Jan. 2020. [Online]. Available: https://erdogant.github.io/ bnlearn\n",
    "figures": [],
    "tables": [],
    "footnotes": []
  }
]